{
  "id": "574",
  "name": "Erik Shoji",
  "url": "https://www.plusliga.pl/statsPlayers/id/574.html",
  "season": "2024-2025",
  "league": "plusliga",
  "team": "ZAKSA Kędzierzyn",
  "season_totals": {
    "matches": 137,
    "sets": 509,
    "points": 0,
    "serve_total": 0,
    "aces": 0,
    "serve_errors": 0,
    "aces_per_set": 0,
    "reception_total": 2096,
    "reception_errors": 140,
    "reception_negative": 460,
    "reception_perfect": 540,
    "reception_perfect_percent": 25.7634,
    "attack_total": 0,
    "attack_errors": 0,
    "attack_blocked": 0,
    "attack_perfect": 0,
    "attack_perfect_percent": 0,
    "block_points": 0,
    "block_points_per_set": 0
  },
  "match_by_match": [
    {
      "match_id": "1103464",
      "opponent": "ZAKSA Kędzierzyn-Koźle -PGE Projekt Warszawa",
      "sets": 3,
      "points_total": 0,
      "points_break": 0,
      "points_balance": 0,
      "serve_total": 0,
      "serve_errors": 0,
      "serve_aces": 0,
      "serve_efficiency": 0,
      "reception_total": 11,
      "reception_errors": 0,
      "reception_positive_percent": 36,
      "reception_perfect_percent": 27,
      "attack_total": 0,
      "attack_errors": 0,
      "attack_blocked": 0,
      "attack_points": 0,
      "attack_success_percent": 0,
      "attack_efficiency": 0,
      "block_points": 0,
      "block_plus": 0,
      "defense": 0,
      "assists": 0,
      "is_home": false,
      "date": "14.09.2024, 14:45",
      "phase": "regular",
      "result": "L",
      "home_team": "PGE Projekt Warszawa",
      "away_team": "ZAKSA Kędzierzyn-Koźle",
      "home_sets": 3,
      "away_sets": 0,
      "match_date": "14.09.2024, 14:45"
    },
    {
      "match_id": "1103613",
      "opponent": "ZAKSA Kędzierzyn-Koźle -Indykpol AZS Olsztyn",
      "sets": 4,
      "points_total": 0,
      "points_break": 0,
      "points_balance": -1,
      "serve_total": 0,
      "serve_errors": 0,
      "serve_aces": 0,
      "serve_efficiency": 0,
      "reception_total": 14,
      "reception_errors": 1,
      "reception_positive_percent": 64,
      "reception_perfect_percent": 36,
      "attack_total": 0,
      "attack_errors": 0,
      "attack_blocked": 0,
      "attack_points": 0,
      "attack_success_percent": 0,
      "attack_efficiency": 0,
      "block_points": 0,
      "block_plus": 0,
      "defense": 0,
      "assists": 0,
      "is_home": false,
      "date": "30.09.2024, 17:30",
      "phase": "regular",
      "result": "W",
      "home_team": "Indykpol AZS Olsztyn",
      "away_team": "ZAKSA Kędzierzyn-Koźle",
      "home_sets": 1,
      "away_sets": 3,
      "match_date": "30.09.2024, 17:30"
    },
    {
      "match_id": "1103630",
      "opponent": "ZAKSA Kędzierzyn-Koźle -Trefl Gdańsk",
      "sets": 3,
      "points_total": 0,
      "points_break": 0,
      "points_balance": -1,
      "serve_total": 0,
      "serve_errors": 0,
      "serve_aces": 0,
      "serve_efficiency": 0,
      "reception_total": 13,
      "reception_errors": 1,
      "reception_positive_percent": 31,
      "reception_perfect_percent": 8,
      "attack_total": 0,
      "attack_errors": 0,
      "attack_blocked": 0,
      "attack_points": 0,
      "attack_success_percent": 0,
      "attack_efficiency": 0,
      "block_points": 0,
      "block_plus": 0,
      "defense": 0,
      "assists": 0,
      "is_home": false,
      "date": "05.10.2024, 17:30",
      "phase": "regular",
      "result": "W",
      "home_team": "Trefl Gdańsk",
      "away_team": "ZAKSA Kędzierzyn-Koźle",
      "home_sets": 0,
      "away_sets": 3,
      "match_date": "05.10.2024, 17:30"
    },
    {
      "match_id": "1103603",
      "opponent": "ZAKSA Kędzierzyn-Koźle -Steam Hemarpol Norwid Częstochowa",
      "sets": 5,
      "points_total": 0,
      "points_break": 0,
      "points_balance": 0,
      "serve_total": 0,
      "serve_errors": 0,
      "serve_aces": 0,
      "serve_efficiency": 0,
      "reception_total": 24,
      "reception_errors": 0,
      "reception_positive_percent": 42,
      "reception_perfect_percent": 21,
      "attack_total": 0,
      "attack_errors": 0,
      "attack_blocked": 0,
      "attack_points": 0,
      "attack_success_percent": 0,
      "attack_efficiency": 0,
      "block_points": 0,
      "block_plus": 0,
      "defense": 0,
      "assists": 0,
      "is_home": false,
      "date": "08.10.2024, 20:30",
      "phase": "regular",
      "result": "W",
      "home_team": "ZAKSA Kędzierzyn-Koźle",
      "away_team": "Steam Hemarpol Norwid Częstochowa",
      "home_sets": 2,
      "away_sets": 3,
      "match_date": "08.10.2024, 20:30"
    },
    {
      "match_id": "1103633",
      "opponent": "ZAKSA Kędzierzyn-Koźle -PGE GiEK SKRA Bełchatów",
      "sets": 4,
      "points_total": 0,
      "points_break": 0,
      "points_balance": 0,
      "serve_total": 0,
      "serve_errors": 0,
      "serve_aces": 0,
      "serve_efficiency": 0,
      "reception_total": 14,
      "reception_errors": 0,
      "reception_positive_percent": 64,
      "reception_perfect_percent": 43,
      "attack_total": 0,
      "attack_errors": 0,
      "attack_blocked": 0,
      "attack_points": 0,
      "attack_success_percent": 0,
      "attack_efficiency": 0,
      "block_points": 0,
      "block_plus": 0,
      "defense": 0,
      "assists": 0,
      "is_home": false,
      "date": "12.10.2024, 14:45",
      "phase": "regular",
      "result": "L",
      "home_team": "ZAKSA Kędzierzyn-Koźle",
      "away_team": "PGE GiEK SKRA Bełchatów",
      "home_sets": 3,
      "away_sets": 1,
      "match_date": "12.10.2024, 14:45"
    },
    {
      "match_id": "1103618",
      "opponent": "ZAKSA Kędzierzyn-Koźle -Cuprum Stilon Gorzów",
      "sets": 4,
      "points_total": 0,
      "points_break": 0,
      "points_balance": 0,
      "serve_total": 0,
      "serve_errors": 0,
      "serve_aces": 0,
      "serve_efficiency": 0,
      "reception_total": 12,
      "reception_errors": 0,
      "reception_positive_percent": 50,
      "reception_perfect_percent": 33,
      "attack_total": 0,
      "attack_errors": 0,
      "attack_blocked": 0,
      "attack_points": 0,
      "attack_success_percent": 0,
      "attack_efficiency": 0,
      "block_points": 0,
      "block_plus": 0,
      "defense": 0,
      "assists": 0,
      "is_home": false,
      "date": "15.10.2024, 17:30",
      "phase": "regular",
      "result": "L",
      "home_team": "ZAKSA Kędzierzyn-Koźle",
      "away_team": "Cuprum Stilon Gorzów",
      "home_sets": 3,
      "away_sets": 1,
      "match_date": "15.10.2024, 17:30"
    },
    {
      "match_id": "1103647",
      "opponent": "ZAKSA Kędzierzyn-Koźle -Ślepsk Malow Suwałki",
      "sets": 5,
      "points_total": 0,
      "points_break": 0,
      "points_balance": -1,
      "serve_total": 0,
      "serve_errors": 0,
      "serve_aces": 0,
      "serve_efficiency": 0,
      "reception_total": 18,
      "reception_errors": 1,
      "reception_positive_percent": 56,
      "reception_perfect_percent": 28,
      "attack_total": 0,
      "attack_errors": 0,
      "attack_blocked": 0,
      "attack_points": 0,
      "attack_success_percent": 0,
      "attack_efficiency": 0,
      "block_points": 0,
      "block_plus": 0,
      "defense": 0,
      "assists": 0,
      "is_home": false,
      "date": "18.10.2024, 17:30",
      "phase": "regular",
      "result": "L",
      "home_team": "Ślepsk Malow Suwałki",
      "away_team": "ZAKSA Kędzierzyn-Koźle",
      "home_sets": 3,
      "away_sets": 2,
      "match_date": "18.10.2024, 17:30"
    },
    {
      "match_id": "1103648",
      "opponent": "ZAKSA Kędzierzyn-Koźle -BOGDANKA LUK Lublin",
      "sets": 3,
      "points_total": 0,
      "points_break": 0,
      "points_balance": -1,
      "serve_total": 0,
      "serve_errors": 0,
      "serve_aces": 0,
      "serve_efficiency": 0,
      "reception_total": 16,
      "reception_errors": 1,
      "reception_positive_percent": 31,
      "reception_perfect_percent": 6,
      "attack_total": 0,
      "attack_errors": 0,
      "attack_blocked": 0,
      "attack_points": 0,
      "attack_success_percent": 0,
      "attack_efficiency": 0,
      "block_points": 0,
      "block_plus": 0,
      "defense": 0,
      "assists": 0,
      "is_home": false,
      "date": "23.10.2024, 20:30",
      "phase": "regular",
      "result": "L",
      "home_team": "BOGDANKA LUK Lublin",
      "away_team": "ZAKSA Kędzierzyn-Koźle",
      "home_sets": 3,
      "away_sets": 0,
      "match_date": "23.10.2024, 20:30"
    },
    {
      "match_id": "1103663",
      "opponent": "ZAKSA Kędzierzyn-Koźle -Nowak-Mosty MKS Będzin",
      "sets": 3,
      "points_total": 0,
      "points_break": 0,
      "points_balance": 0,
      "serve_total": 0,
      "serve_errors": 0,
      "serve_aces": 0,
      "serve_efficiency": 0,
      "reception_total": 5,
      "reception_errors": 0,
      "reception_positive_percent": 60,
      "reception_perfect_percent": 60,
      "attack_total": 0,
      "attack_errors": 0,
      "attack_blocked": 0,
      "attack_points": 0,
      "attack_success_percent": 0,
      "attack_efficiency": 0,
      "block_points": 0,
      "block_plus": 0,
      "defense": 0,
      "assists": 0,
      "is_home": false,
      "date": "29.10.2024, 17:30",
      "phase": "regular",
      "result": "L",
      "home_team": "ZAKSA Kędzierzyn-Koźle",
      "away_team": "Nowak-Mosty MKS Będzin",
      "home_sets": 3,
      "away_sets": 0,
      "match_date": "29.10.2024, 17:30"
    },
    {
      "match_id": "1103666",
      "opponent": "ZAKSA Kędzierzyn-Koźle -PSG Stal Nysa",
      "sets": 4,
      "points_total": 0,
      "points_break": 0,
      "points_balance": 0,
      "serve_total": 0,
      "serve_errors": 0,
      "serve_aces": 0,
      "serve_efficiency": 0,
      "reception_total": 15,
      "reception_errors": 0,
      "reception_positive_percent": 47,
      "reception_perfect_percent": 27,
      "attack_total": 0,
      "attack_errors": 0,
      "attack_blocked": 0,
      "attack_points": 0,
      "attack_success_percent": 0,
      "attack_efficiency": 0,
      "block_points": 0,
      "block_plus": 0,
      "defense": 0,
      "assists": 0,
      "is_home": false,
      "date": "03.11.2024, 14:45",
      "phase": "regular",
      "result": "W",
      "home_team": "PSG Stal Nysa",
      "away_team": "ZAKSA Kędzierzyn-Koźle",
      "home_sets": 1,
      "away_sets": 3,
      "match_date": "03.11.2024, 14:45"
    },
    {
      "match_id": "1103678",
      "opponent": "ZAKSA Kędzierzyn-Koźle -JSW Jastrzębski Węgiel",
      "sets": 4,
      "points_total": 0,
      "points_break": 0,
      "points_balance": 0,
      "serve_total": 0,
      "serve_errors": 0,
      "serve_aces": 0,
      "serve_efficiency": 0,
      "reception_total": 17,
      "reception_errors": 0,
      "reception_positive_percent": 53,
      "reception_perfect_percent": 35,
      "attack_total": 0,
      "attack_errors": 0,
      "attack_blocked": 0,
      "attack_points": 0,
      "attack_success_percent": 0,
      "attack_efficiency": 0,
      "block_points": 0,
      "block_plus": 0,
      "defense": 0,
      "assists": 0,
      "is_home": false,
      "date": "09.11.2024, 14:45",
      "phase": "regular",
      "result": "L",
      "home_team": "ZAKSA Kędzierzyn-Koźle",
      "away_team": "JSW Jastrzębski Węgiel",
      "home_sets": 3,
      "away_sets": 1,
      "match_date": "09.11.2024, 14:45"
    },
    {
      "match_id": "1103699",
      "opponent": "ZAKSA Kędzierzyn-Koźle -Asseco Resovia Rzeszów",
      "sets": 5,
      "points_total": 0,
      "points_break": 0,
      "points_balance": 0,
      "serve_total": 0,
      "serve_errors": 0,
      "serve_aces": 0,
      "serve_efficiency": 0,
      "reception_total": 15,
      "reception_errors": 0,
      "reception_positive_percent": 53,
      "reception_perfect_percent": 7,
      "attack_total": 0,
      "attack_errors": 0,
      "attack_blocked": 0,
      "attack_points": 0,
      "attack_success_percent": 0,
      "attack_efficiency": 0,
      "block_points": 0,
      "block_plus": 0,
      "defense": 0,
      "assists": 0,
      "is_home": false,
      "date": "30.11.2024, 14:45",
      "phase": "regular",
      "result": "W",
      "home_team": "Asseco Resovia Rzeszów",
      "away_team": "ZAKSA Kędzierzyn-Koźle",
      "home_sets": 2,
      "away_sets": 3,
      "match_date": "30.11.2024, 14:45"
    },
    {
      "match_id": "1103708",
      "opponent": "ZAKSA Kędzierzyn-Koźle -GKS Katowice",
      "sets": 2,
      "points_total": 0,
      "points_break": 0,
      "points_balance": -1,
      "serve_total": 0,
      "serve_errors": 0,
      "serve_aces": 0,
      "serve_efficiency": 0,
      "reception_total": 9,
      "reception_errors": 1,
      "reception_positive_percent": 56,
      "reception_perfect_percent": 11,
      "attack_total": 0,
      "attack_errors": 0,
      "attack_blocked": 0,
      "attack_points": 0,
      "attack_success_percent": 0,
      "attack_efficiency": 0,
      "block_points": 0,
      "block_plus": 0,
      "defense": 0,
      "assists": 0,
      "is_home": false,
      "date": "07.12.2024, 20:30",
      "phase": "regular",
      "result": "L",
      "home_team": "ZAKSA Kędzierzyn-Koźle",
      "away_team": "GKS Katowice",
      "home_sets": 3,
      "away_sets": 1,
      "match_date": "07.12.2024, 20:30"
    },
    {
      "match_id": "1103716",
      "opponent": "ZAKSA Kędzierzyn-Koźle -PGE Projekt Warszawa",
      "sets": 3,
      "points_total": 0,
      "points_break": 0,
      "points_balance": -1,
      "serve_total": 0,
      "serve_errors": 0,
      "serve_aces": 0,
      "serve_efficiency": 0,
      "reception_total": 16,
      "reception_errors": 1,
      "reception_positive_percent": 63,
      "reception_perfect_percent": 25,
      "attack_total": 0,
      "attack_errors": 0,
      "attack_blocked": 0,
      "attack_points": 0,
      "attack_success_percent": 0,
      "attack_efficiency": 0,
      "block_points": 0,
      "block_plus": 0,
      "defense": 0,
      "assists": 0,
      "is_home": false,
      "date": "12.12.2024, 17:30",
      "phase": "regular",
      "result": "W",
      "home_team": "ZAKSA Kędzierzyn-Koźle",
      "away_team": "PGE Projekt Warszawa",
      "home_sets": 0,
      "away_sets": 3,
      "match_date": "12.12.2024, 17:30"
    },
    {
      "match_id": "1103723",
      "opponent": "ZAKSA Kędzierzyn-Koźle -Steam Hemarpol Norwid Częstochowa",
      "sets": 3,
      "points_total": 0,
      "points_break": 0,
      "points_balance": -1,
      "serve_total": 0,
      "serve_errors": 0,
      "serve_aces": 0,
      "serve_efficiency": 0,
      "reception_total": 13,
      "reception_errors": 1,
      "reception_positive_percent": 38,
      "reception_perfect_percent": 15,
      "attack_total": 0,
      "attack_errors": 0,
      "attack_blocked": 0,
      "attack_points": 0,
      "attack_success_percent": 0,
      "attack_efficiency": 0,
      "block_points": 0,
      "block_plus": 0,
      "defense": 7,
      "assists": 1,
      "is_home": false,
      "date": "20.12.2024, 20:30",
      "phase": "regular",
      "result": "W",
      "home_team": "Steam Hemarpol Norwid Częstochowa",
      "away_team": "ZAKSA Kędzierzyn-Koźle",
      "home_sets": 0,
      "away_sets": 3,
      "match_date": "20.12.2024, 20:30"
    },
    {
      "match_id": "1103737",
      "opponent": "ZAKSA Kędzierzyn-Koźle -Cuprum Stilon Gorzów",
      "sets": 4,
      "points_total": 0,
      "points_break": 0,
      "points_balance": 0,
      "serve_total": 0,
      "serve_errors": 0,
      "serve_aces": 0,
      "serve_efficiency": 0,
      "reception_total": 11,
      "reception_errors": 0,
      "reception_positive_percent": 82,
      "reception_perfect_percent": 18,
      "attack_total": 0,
      "attack_errors": 0,
      "attack_blocked": 0,
      "attack_points": 0,
      "attack_success_percent": 0,
      "attack_efficiency": 0,
      "block_points": 0,
      "block_plus": 0,
      "defense": 11,
      "assists": 2,
      "is_home": false,
      "date": "05.01.2025, 17:30",
      "phase": "regular",
      "result": "W",
      "home_team": "Cuprum Stilon Gorzów",
      "away_team": "ZAKSA Kędzierzyn-Koźle",
      "home_sets": 1,
      "away_sets": 3,
      "match_date": "05.01.2025, 17:30"
    },
    {
      "match_id": "1103749",
      "opponent": "ZAKSA Kędzierzyn-Koźle -Trefl Gdańsk",
      "sets": 4,
      "points_total": 0,
      "points_break": 0,
      "points_balance": -1,
      "serve_total": 0,
      "serve_errors": 0,
      "serve_aces": 0,
      "serve_efficiency": 0,
      "reception_total": 8,
      "reception_errors": 1,
      "reception_positive_percent": 38,
      "reception_perfect_percent": 25,
      "attack_total": 0,
      "attack_errors": 0,
      "attack_blocked": 0,
      "attack_points": 0,
      "attack_success_percent": 0,
      "attack_efficiency": 0,
      "block_points": 0,
      "block_plus": 0,
      "defense": 7,
      "assists": 1,
      "is_home": false,
      "date": "13.01.2025, 17:30",
      "phase": "regular",
      "result": "L",
      "home_team": "ZAKSA Kędzierzyn-Koźle",
      "away_team": "Trefl Gdańsk",
      "home_sets": 3,
      "away_sets": 1,
      "match_date": "13.01.2025, 17:30"
    },
    {
      "match_id": "1103752",
      "opponent": "ZAKSA Kędzierzyn-Koźle -PGE GiEK SKRA Bełchatów",
      "sets": 5,
      "points_total": 0,
      "points_break": 0,
      "points_balance": -1,
      "serve_total": 0,
      "serve_errors": 0,
      "serve_aces": 0,
      "serve_efficiency": 0,
      "reception_total": 16,
      "reception_errors": 1,
      "reception_positive_percent": 44,
      "reception_perfect_percent": 25,
      "attack_total": 0,
      "attack_errors": 0,
      "attack_blocked": 0,
      "attack_points": 0,
      "attack_success_percent": 0,
      "attack_efficiency": 0,
      "block_points": 0,
      "block_plus": 0,
      "defense": 6,
      "assists": 2,
      "is_home": false,
      "date": "19.01.2025, 14:45",
      "phase": "regular",
      "result": "W",
      "home_team": "PGE GiEK SKRA Bełchatów",
      "away_team": "ZAKSA Kędzierzyn-Koźle",
      "home_sets": 2,
      "away_sets": 3,
      "match_date": "19.01.2025, 14:45"
    },
    {
      "match_id": "1103766",
      "opponent": "ZAKSA Kędzierzyn-Koźle -Ślepsk Malow Suwałki",
      "sets": 4,
      "points_total": 0,
      "points_break": 0,
      "points_balance": 0,
      "serve_total": 0,
      "serve_errors": 0,
      "serve_aces": 0,
      "serve_efficiency": 0,
      "reception_total": 14,
      "reception_errors": 0,
      "reception_positive_percent": 57,
      "reception_perfect_percent": 21,
      "attack_total": 0,
      "attack_errors": 0,
      "attack_blocked": 0,
      "attack_points": 0,
      "attack_success_percent": 0,
      "attack_efficiency": 0,
      "block_points": 0,
      "block_plus": 0,
      "defense": 7,
      "assists": 3,
      "is_home": false,
      "date": "26.01.2025, 14:45",
      "phase": "regular",
      "result": "L",
      "home_team": "ZAKSA Kędzierzyn-Koźle",
      "away_team": "Ślepsk Malow Suwałki",
      "home_sets": 3,
      "away_sets": 1,
      "match_date": "26.01.2025, 14:45"
    },
    {
      "match_id": "1103767",
      "opponent": "ZAKSA Kędzierzyn-Koźle -BOGDANKA LUK Lublin",
      "sets": 5,
      "points_total": 0,
      "points_break": 0,
      "points_balance": 0,
      "serve_total": 0,
      "serve_errors": 0,
      "serve_aces": 0,
      "serve_efficiency": 0,
      "reception_total": 11,
      "reception_errors": 0,
      "reception_positive_percent": 36,
      "reception_perfect_percent": 18,
      "attack_total": 0,
      "attack_errors": 0,
      "attack_blocked": 0,
      "attack_points": 0,
      "attack_success_percent": 0,
      "attack_efficiency": 0,
      "block_points": 0,
      "block_plus": 0,
      "defense": 12,
      "assists": 1,
      "is_home": false,
      "date": "01.02.2025, 14:45",
      "phase": "regular",
      "result": "L",
      "home_team": "ZAKSA Kędzierzyn-Koźle",
      "away_team": "BOGDANKA LUK Lublin",
      "home_sets": 3,
      "away_sets": 2,
      "match_date": "01.02.2025, 14:45"
    },
    {
      "match_id": "1103782",
      "opponent": "ZAKSA Kędzierzyn-Koźle -Nowak-Mosty MKS Będzin",
      "sets": 3,
      "points_total": 0,
      "points_break": 0,
      "points_balance": 0,
      "serve_total": 0,
      "serve_errors": 0,
      "serve_aces": 0,
      "serve_efficiency": 0,
      "reception_total": 12,
      "reception_errors": 0,
      "reception_positive_percent": 67,
      "reception_perfect_percent": 33,
      "attack_total": 0,
      "attack_errors": 0,
      "attack_blocked": 0,
      "attack_points": 0,
      "attack_success_percent": 0,
      "attack_efficiency": 0,
      "block_points": 0,
      "block_plus": 0,
      "defense": 6,
      "assists": 2,
      "is_home": false,
      "date": "10.02.2025, 20:30",
      "phase": "regular",
      "result": "W",
      "home_team": "Nowak-Mosty MKS Będzin",
      "away_team": "ZAKSA Kędzierzyn-Koźle",
      "home_sets": 0,
      "away_sets": 3,
      "match_date": "10.02.2025, 20:30"
    },
    {
      "match_id": "1103785",
      "opponent": "ZAKSA Kędzierzyn-Koźle -PSG Stal Nysa",
      "sets": 5,
      "points_total": 0,
      "points_break": 0,
      "points_balance": -3,
      "serve_total": 0,
      "serve_errors": 0,
      "serve_aces": 0,
      "serve_efficiency": 0,
      "reception_total": 18,
      "reception_errors": 3,
      "reception_positive_percent": 28,
      "reception_perfect_percent": 6,
      "attack_total": 0,
      "attack_errors": 0,
      "attack_blocked": 0,
      "attack_points": 0,
      "attack_success_percent": 0,
      "attack_efficiency": 0,
      "block_points": 0,
      "block_plus": 0,
      "defense": 12,
      "assists": 0,
      "is_home": false,
      "date": "13.02.2025, 17:30",
      "phase": "regular",
      "result": "L",
      "home_team": "ZAKSA Kędzierzyn-Koźle",
      "away_team": "PSG Stal Nysa",
      "home_sets": 3,
      "away_sets": 2,
      "match_date": "13.02.2025, 17:30"
    },
    {
      "match_id": "1103797",
      "opponent": "ZAKSA Kędzierzyn-Koźle -JSW Jastrzębski Węgiel",
      "sets": 3,
      "points_total": 0,
      "points_break": 0,
      "points_balance": -1,
      "serve_total": 0,
      "serve_errors": 0,
      "serve_aces": 0,
      "serve_efficiency": 0,
      "reception_total": 17,
      "reception_errors": 1,
      "reception_positive_percent": 41,
      "reception_perfect_percent": 12,
      "attack_total": 0,
      "attack_errors": 0,
      "attack_blocked": 0,
      "attack_points": 0,
      "attack_success_percent": 0,
      "attack_efficiency": 0,
      "block_points": 0,
      "block_plus": 0,
      "defense": 8,
      "assists": 4,
      "is_home": false,
      "date": "23.02.2025, 14:45",
      "phase": "regular",
      "result": "L",
      "home_team": "JSW Jastrzębski Węgiel",
      "away_team": "ZAKSA Kędzierzyn-Koźle",
      "home_sets": 3,
      "away_sets": 0,
      "match_date": "23.02.2025, 14:45"
    },
    {
      "match_id": "1103732",
      "opponent": "ZAKSA Kędzierzyn-Koźle -Indykpol AZS Olsztyn",
      "sets": 3,
      "points_total": 0,
      "points_break": 0,
      "points_balance": 0,
      "serve_total": 0,
      "serve_errors": 0,
      "serve_aces": 0,
      "serve_efficiency": 0,
      "reception_total": 5,
      "reception_errors": 0,
      "reception_positive_percent": 40,
      "reception_perfect_percent": 40,
      "attack_total": 0,
      "attack_errors": 0,
      "attack_blocked": 0,
      "attack_points": 0,
      "attack_success_percent": 0,
      "attack_efficiency": 0,
      "block_points": 0,
      "block_plus": 0,
      "defense": 6,
      "assists": 2,
      "is_home": false,
      "date": "27.02.2025, 20:30",
      "phase": "regular",
      "result": "L",
      "home_team": "ZAKSA Kędzierzyn-Koźle",
      "away_team": "Indykpol AZS Olsztyn",
      "home_sets": 3,
      "away_sets": 0,
      "match_date": "27.02.2025, 20:30"
    },
    {
      "match_id": "1103801",
      "opponent": "ZAKSA Kędzierzyn-Koźle -Aluron CMC Warta Zawiercie",
      "sets": 3,
      "points_total": 0,
      "points_break": 0,
      "points_balance": -3,
      "serve_total": 0,
      "serve_errors": 0,
      "serve_aces": 0,
      "serve_efficiency": 0,
      "reception_total": 17,
      "reception_errors": 3,
      "reception_positive_percent": 29,
      "reception_perfect_percent": 12,
      "attack_total": 0,
      "attack_errors": 0,
      "attack_blocked": 0,
      "attack_points": 0,
      "attack_success_percent": 0,
      "attack_efficiency": 0,
      "block_points": 0,
      "block_plus": 0,
      "defense": 8,
      "assists": 2,
      "is_home": false,
      "date": "02.03.2025, 14:45",
      "phase": "regular",
      "result": "W",
      "home_team": "ZAKSA Kędzierzyn-Koźle",
      "away_team": "Aluron CMC Warta Zawiercie",
      "home_sets": 0,
      "away_sets": 3,
      "match_date": "02.03.2025, 14:45"
    },
    {
      "match_id": "1103812",
      "opponent": "ZAKSA Kędzierzyn-Koźle -Barkom Każany Lwów",
      "sets": 4,
      "points_total": 0,
      "points_break": 0,
      "points_balance": -2,
      "serve_total": 0,
      "serve_errors": 0,
      "serve_aces": 0,
      "serve_efficiency": 0,
      "reception_total": 17,
      "reception_errors": 2,
      "reception_positive_percent": 35,
      "reception_perfect_percent": 18,
      "attack_total": 0,
      "attack_errors": 0,
      "attack_blocked": 0,
      "attack_points": 0,
      "attack_success_percent": 0,
      "attack_efficiency": 0,
      "block_points": 0,
      "block_plus": 0,
      "defense": 6,
      "assists": 2,
      "is_home": false,
      "date": "06.03.2025, 17:30",
      "phase": "regular",
      "result": "W",
      "home_team": "Barkom Każany Lwów",
      "away_team": "ZAKSA Kędzierzyn-Koźle",
      "home_sets": 1,
      "away_sets": 3,
      "match_date": "06.03.2025, 17:30"
    },
    {
      "match_id": "1103818",
      "opponent": "ZAKSA Kędzierzyn-Koźle -Asseco Resovia Rzeszów",
      "sets": 5,
      "points_total": 0,
      "points_break": 0,
      "points_balance": 0,
      "serve_total": 0,
      "serve_errors": 0,
      "serve_aces": 0,
      "serve_efficiency": 0,
      "reception_total": 13,
      "reception_errors": 0,
      "reception_positive_percent": 54,
      "reception_perfect_percent": 15,
      "attack_total": 0,
      "attack_errors": 0,
      "attack_blocked": 0,
      "attack_points": 0,
      "attack_success_percent": 0,
      "attack_efficiency": 0,
      "block_points": 0,
      "block_plus": 0,
      "defense": 14,
      "assists": 2,
      "is_home": false,
      "date": "15.03.2025, 17:30",
      "phase": "regular",
      "result": "W",
      "home_team": "ZAKSA Kędzierzyn-Koźle",
      "away_team": "Asseco Resovia Rzeszów",
      "home_sets": 2,
      "away_sets": 3,
      "match_date": "15.03.2025, 17:30"
    },
    {
      "match_id": "1103827",
      "opponent": "ZAKSA Kędzierzyn-Koźle -GKS Katowice",
      "sets": 3,
      "points_total": 0,
      "points_break": 0,
      "points_balance": 0,
      "serve_total": 0,
      "serve_errors": 0,
      "serve_aces": 0,
      "serve_efficiency": 0,
      "reception_total": 5,
      "reception_errors": 0,
      "reception_positive_percent": 40,
      "reception_perfect_percent": 20,
      "attack_total": 0,
      "attack_errors": 0,
      "attack_blocked": 0,
      "attack_points": 0,
      "attack_success_percent": 0,
      "attack_efficiency": 0,
      "block_points": 0,
      "block_plus": 0,
      "defense": 3,
      "assists": 1,
      "is_home": false,
      "date": "21.03.2025, 20:30",
      "phase": "regular",
      "result": "W",
      "home_team": "GKS Katowice",
      "away_team": "ZAKSA Kędzierzyn-Koźle",
      "home_sets": 0,
      "away_sets": 3,
      "match_date": "21.03.2025, 20:30"
    },
    {
      "match_id": "1104112",
      "opponent": "ZAKSA Kędzierzyn-Koźle -BOGDANKA LUK Lublin",
      "sets": 4,
      "points_total": 0,
      "points_break": 0,
      "points_balance": -1,
      "serve_total": 0,
      "serve_errors": 0,
      "serve_aces": 0,
      "serve_efficiency": 0,
      "reception_total": 12,
      "reception_errors": 1,
      "reception_positive_percent": 25,
      "reception_perfect_percent": 17,
      "attack_total": 0,
      "attack_errors": 0,
      "attack_blocked": 0,
      "attack_points": 0,
      "attack_success_percent": 0,
      "attack_efficiency": 0,
      "block_points": 0,
      "block_plus": 0,
      "defense": 9,
      "assists": 4,
      "is_home": false,
      "date": "29.03.2025, 17:30",
      "phase": "playoff",
      "result": "W",
      "home_team": "BOGDANKA LUK Lublin",
      "away_team": "ZAKSA Kędzierzyn-Koźle",
      "home_sets": 1,
      "away_sets": 3,
      "match_date": "29.03.2025, 17:30"
    },
    {
      "match_id": "1104111",
      "opponent": "ZAKSA Kędzierzyn-Koźle -BOGDANKA LUK Lublin",
      "sets": 3,
      "points_total": 0,
      "points_break": 0,
      "points_balance": -1,
      "serve_total": 0,
      "serve_errors": 0,
      "serve_aces": 0,
      "serve_efficiency": 0,
      "reception_total": 13,
      "reception_errors": 1,
      "reception_positive_percent": 69,
      "reception_perfect_percent": 31,
      "attack_total": 0,
      "attack_errors": 0,
      "attack_blocked": 0,
      "attack_points": 0,
      "attack_success_percent": 0,
      "attack_efficiency": 0,
      "block_points": 0,
      "block_plus": 0,
      "defense": 6,
      "assists": 2,
      "is_home": false,
      "date": "01.04.2025, 20:30",
      "phase": "playoff",
      "result": "W",
      "home_team": "ZAKSA Kędzierzyn-Koźle",
      "away_team": "BOGDANKA LUK Lublin",
      "home_sets": 0,
      "away_sets": 3,
      "match_date": "01.04.2025, 20:30"
    },
    {
      "match_id": "1104114",
      "opponent": "ZAKSA Kędzierzyn-Koźle -BOGDANKA LUK Lublin",
      "sets": 3,
      "points_total": 0,
      "points_break": 0,
      "points_balance": -1,
      "serve_total": 0,
      "serve_errors": 0,
      "serve_aces": 0,
      "serve_efficiency": 0,
      "reception_total": 15,
      "reception_errors": 1,
      "reception_positive_percent": 13,
      "reception_perfect_percent": 13,
      "attack_total": 0,
      "attack_errors": 0,
      "attack_blocked": 0,
      "attack_points": 0,
      "attack_success_percent": 0,
      "attack_efficiency": 0,
      "block_points": 0,
      "block_plus": 0,
      "defense": 7,
      "assists": 1,
      "is_home": false,
      "date": "06.04.2025, 14:45",
      "phase": "playoff",
      "result": "L",
      "home_team": "BOGDANKA LUK Lublin",
      "away_team": "ZAKSA Kędzierzyn-Koźle",
      "home_sets": 3,
      "away_sets": 0,
      "match_date": "06.04.2025, 14:45"
    },
    {
      "match_id": "1104122",
      "opponent": "ZAKSA Kędzierzyn-Koźle -Asseco Resovia Rzeszów",
      "sets": 4,
      "points_total": 0,
      "points_break": 0,
      "points_balance": 0,
      "serve_total": 0,
      "serve_errors": 0,
      "serve_aces": 0,
      "serve_efficiency": 0,
      "reception_total": 17,
      "reception_errors": 0,
      "reception_positive_percent": 76,
      "reception_perfect_percent": 35,
      "attack_total": 0,
      "attack_errors": 0,
      "attack_blocked": 0,
      "attack_points": 0,
      "attack_success_percent": 0,
      "attack_efficiency": 0,
      "block_points": 0,
      "block_plus": 0,
      "defense": 6,
      "assists": 2,
      "is_home": false,
      "date": "19.04.2025, 17:30",
      "phase": "playoff",
      "result": "W",
      "home_team": "Asseco Resovia Rzeszów",
      "away_team": "ZAKSA Kędzierzyn-Koźle",
      "home_sets": 1,
      "away_sets": 3,
      "match_date": "19.04.2025, 17:30"
    },
    {
      "match_id": "1104126",
      "opponent": "ZAKSA Kędzierzyn-Koźle -Asseco Resovia Rzeszów",
      "sets": 4,
      "points_total": 0,
      "points_break": 0,
      "points_balance": -2,
      "serve_total": 0,
      "serve_errors": 0,
      "serve_aces": 0,
      "serve_efficiency": 0,
      "reception_total": 13,
      "reception_errors": 2,
      "reception_positive_percent": 38,
      "reception_perfect_percent": 8,
      "attack_total": 0,
      "attack_errors": 0,
      "attack_blocked": 0,
      "attack_points": 0,
      "attack_success_percent": 0,
      "attack_efficiency": 0,
      "block_points": 0,
      "block_plus": 0,
      "defense": 22,
      "assists": 0,
      "is_home": false,
      "date": "24.04.2025, 17:30",
      "phase": "playoff",
      "result": "L",
      "home_team": "ZAKSA Kędzierzyn-Koźle",
      "away_team": "Asseco Resovia Rzeszów",
      "home_sets": 3,
      "away_sets": 2,
      "match_date": "24.04.2025, 17:30"
    },
    {
      "match_id": null,
      "opponent": "Łącznie (33)",
      "sets": 124,
      "points_total": 0,
      "points_break": 0,
      "points_balance": -23,
      "serve_total": 0,
      "serve_errors": 0,
      "serve_aces": 0,
      "serve_efficiency": 0,
      "reception_total": 446,
      "reception_errors": 23,
      "reception_positive_percent": 47,
      "reception_perfect_percent": 22,
      "attack_total": 0,
      "attack_errors": 0,
      "attack_blocked": 0,
      "attack_points": 0,
      "attack_success_percent": 0,
      "attack_efficiency": 0,
      "block_points": 0,
      "block_plus": 0,
      "defense": 163,
      "assists": 34,
      "is_home": true
    },
    {
      "match_id": null,
      "opponent": "Średnia meczowa",
      "sets": 3.76,
      "points_total": 0,
      "points_break": 0,
      "points_balance": -0.7,
      "serve_total": 0,
      "serve_errors": 0,
      "serve_aces": 0,
      "serve_efficiency": 0,
      "reception_total": 13.52,
      "reception_errors": 0.7,
      "reception_positive_percent": 1.42,
      "reception_perfect_percent": 0.65,
      "attack_total": 0,
      "attack_errors": 0,
      "attack_blocked": 0,
      "attack_points": 0,
      "attack_success_percent": 0,
      "attack_efficiency": 0,
      "block_points": 0,
      "block_plus": 0,
      "defense": 4.94,
      "assists": 1.03,
      "is_home": true
    }
  ],
  "matches_count": 35,
  "scraped_at": "2025-11-08T23:17:48.470Z"
}