{
  "id": "118",
  "name": "Aleksandra Wenerska",
  "url": "https://www.tauronliga.pl/statsPlayers/id/118.html",
  "season": "2024-2025",
  "team": "PGE Grot Budowlani Łódź",
  "season_totals": {
    "matches": 271,
    "sets": 916,
    "points": 2296,
    "serve_total": 2883,
    "aces": 147,
    "serve_errors": 241,
    "aces_per_set": 0.1605,
    "reception_total": 5938,
    "reception_errors": 454,
    "reception_negative": 1803,
    "reception_perfect": 1140,
    "reception_perfect_percent": 19.1984,
    "attack_total": 5311,
    "attack_errors": 426,
    "attack_blocked": 549,
    "attack_perfect": 1940,
    "attack_perfect_percent": 36.528,
    "block_points": 209,
    "block_points_per_set": 0.2282
  },
  "match_by_match": [
    {
      "match_id": "1103489",
      "opponent": "PGE Grot Budowlani Łódź -Sokół & Hagric Mogilno",
      "sets": 2,
      "points_total": 3,
      "points_break": 0,
      "points_balance": 3,
      "serve_total": 6,
      "serve_errors": 0,
      "serve_aces": 0,
      "serve_efficiency": 0,
      "reception_total": 8,
      "reception_errors": 0,
      "reception_positive_percent": 50,
      "reception_perfect_percent": 13,
      "attack_total": 7,
      "attack_errors": 0,
      "attack_blocked": 0,
      "attack_points": 3,
      "attack_success_percent": 42,
      "attack_efficiency": 42,
      "block_points": 0,
      "block_plus": 0,
      "defense": 0,
      "assists": 0,
      "is_home": true,
      "phase": "regular",
      "home_sets": 3,
      "away_sets": 0,
      "date": "19.10.2024, 19:00",
      "home_team": "PGE Grot Budowlani Łódź",
      "away_team": "Sokół & Hagric Mogilno"
    },
    {
      "match_id": "1103511",
      "opponent": "PGE Grot Budowlani Łódź -Metalkas Pałac Bydgoszcz",
      "sets": 4,
      "points_total": 13,
      "points_break": 6,
      "points_balance": 9,
      "serve_total": 12,
      "serve_errors": 0,
      "serve_aces": 1,
      "serve_efficiency": 8,
      "reception_total": 27,
      "reception_errors": 2,
      "reception_positive_percent": 33,
      "reception_perfect_percent": 15,
      "attack_total": 34,
      "attack_errors": 2,
      "attack_blocked": 4,
      "attack_points": 10,
      "attack_success_percent": 29,
      "attack_efficiency": 11,
      "block_points": 2,
      "block_plus": 2,
      "defense": 0,
      "assists": 0,
      "is_home": true,
      "phase": "regular",
      "home_sets": 3,
      "away_sets": 1,
      "date": "18.11.2024, 19:00",
      "home_team": "PGE Grot Budowlani Łódź",
      "away_team": "Metalkas Pałac Bydgoszcz"
    },
    {
      "match_id": "1103521",
      "opponent": "PGE Grot Budowlani Łódź -#VolleyWrocław",
      "sets": 1,
      "points_total": 0,
      "points_break": 0,
      "points_balance": -1,
      "serve_total": 0,
      "serve_errors": 0,
      "serve_aces": 0,
      "serve_efficiency": 0,
      "reception_total": 4,
      "reception_errors": 1,
      "reception_positive_percent": 0,
      "reception_perfect_percent": 0,
      "attack_total": 0,
      "attack_errors": 0,
      "attack_blocked": 0,
      "attack_points": 0,
      "attack_success_percent": 0,
      "attack_efficiency": 0,
      "block_points": 0,
      "block_plus": 0,
      "defense": 0,
      "assists": 0,
      "is_home": true,
      "phase": "regular",
      "home_sets": 0,
      "away_sets": 3,
      "date": "22.11.2024, 17:30",
      "home_team": "#VolleyWrocław",
      "away_team": "PGE Grot Budowlani Łódź"
    },
    {
      "match_id": "1103522",
      "opponent": "PGE Grot Budowlani Łódź -LOTTO Chemik Police",
      "sets": 1,
      "points_total": 2,
      "points_break": 1,
      "points_balance": 2,
      "serve_total": 3,
      "serve_errors": 0,
      "serve_aces": 0,
      "serve_efficiency": 0,
      "reception_total": 7,
      "reception_errors": 0,
      "reception_positive_percent": 14,
      "reception_perfect_percent": 14,
      "attack_total": 5,
      "attack_errors": 0,
      "attack_blocked": 0,
      "attack_points": 2,
      "attack_success_percent": 40,
      "attack_efficiency": 40,
      "block_points": 0,
      "block_plus": 0,
      "defense": 0,
      "assists": 0,
      "is_home": true,
      "phase": "regular",
      "home_sets": 1,
      "away_sets": 3,
      "date": "02.12.2024, 17:30",
      "home_team": "LOTTO Chemik Police",
      "away_team": "PGE Grot Budowlani Łódź"
    },
    {
      "match_id": "1103532",
      "opponent": "PGE Grot Budowlani Łódź -ŁKS Commercecon Łódź",
      "sets": 1,
      "points_total": 1,
      "points_break": 0,
      "points_balance": 1,
      "serve_total": 1,
      "serve_errors": 0,
      "serve_aces": 0,
      "serve_efficiency": 0,
      "reception_total": 5,
      "reception_errors": 0,
      "reception_positive_percent": 20,
      "reception_perfect_percent": 20,
      "attack_total": 3,
      "attack_errors": 0,
      "attack_blocked": 1,
      "attack_points": 1,
      "attack_success_percent": 33,
      "attack_efficiency": 0,
      "block_points": 0,
      "block_plus": 0,
      "defense": 0,
      "assists": 0,
      "is_home": true,
      "phase": "regular",
      "home_sets": 0,
      "away_sets": 3,
      "date": "06.12.2024, 17:30",
      "home_team": "PGE Grot Budowlani Łódź",
      "away_team": "ŁKS Commercecon Łódź"
    },
    {
      "match_id": "1103566",
      "opponent": "PGE Grot Budowlani Łódź -KS DevelopRes Rzeszów",
      "sets": 1,
      "points_total": 0,
      "points_break": 0,
      "points_balance": 0,
      "serve_total": 0,
      "serve_errors": 0,
      "serve_aces": 0,
      "serve_efficiency": 0,
      "reception_total": 2,
      "reception_errors": 0,
      "reception_positive_percent": 50,
      "reception_perfect_percent": 0,
      "attack_total": 1,
      "attack_errors": 0,
      "attack_blocked": 0,
      "attack_points": 0,
      "attack_success_percent": 0,
      "attack_efficiency": 0,
      "block_points": 0,
      "block_plus": 1,
      "defense": 0,
      "assists": 0,
      "is_home": true,
      "phase": "regular",
      "home_sets": 3,
      "away_sets": 1,
      "date": "31.01.2025, 17:30",
      "home_team": "KS DevelopRes Rzeszów",
      "away_team": "PGE Grot Budowlani Łódź"
    },
    {
      "match_id": "1103587",
      "opponent": "PGE Grot Budowlani Łódź -#VolleyWrocław",
      "sets": 2,
      "points_total": 0,
      "points_break": 0,
      "points_balance": -1,
      "serve_total": 0,
      "serve_errors": 0,
      "serve_aces": 0,
      "serve_efficiency": 0,
      "reception_total": 3,
      "reception_errors": 1,
      "reception_positive_percent": 0,
      "reception_perfect_percent": 0,
      "attack_total": 0,
      "attack_errors": 0,
      "attack_blocked": 0,
      "attack_points": 0,
      "attack_success_percent": 0,
      "attack_efficiency": 0,
      "block_points": 0,
      "block_plus": 0,
      "defense": 0,
      "assists": 0,
      "is_home": true,
      "phase": "regular",
      "home_sets": 3,
      "away_sets": 0,
      "date": "01.03.2025, 19:00",
      "home_team": "PGE Grot Budowlani Łódź",
      "away_team": "#VolleyWrocław"
    },
    {
      "match_id": "1104100",
      "opponent": "PGE Grot Budowlani Łódź -BKS BOSTIK ZGO Bielsko-Biała",
      "sets": 2,
      "points_total": 1,
      "points_break": 1,
      "points_balance": -1,
      "serve_total": 0,
      "serve_errors": 0,
      "serve_aces": 0,
      "serve_efficiency": 0,
      "reception_total": 4,
      "reception_errors": 0,
      "reception_positive_percent": 50,
      "reception_perfect_percent": 0,
      "attack_total": 5,
      "attack_errors": 2,
      "attack_blocked": 0,
      "attack_points": 0,
      "attack_success_percent": 0,
      "attack_efficiency": -40,
      "block_points": 1,
      "block_plus": 0,
      "defense": 2,
      "assists": 0,
      "is_home": true,
      "phase": "playoff",
      "home_sets": 2,
      "away_sets": 3,
      "date": "19.04.2025, 12:30",
      "home_team": "BKS BOSTIK ZGO Bielsko-Biała",
      "away_team": "PGE Grot Budowlani Łódź"
    },
    {
      "match_id": "1104095",
      "opponent": "PGE Grot Budowlani Łódź -BKS BOSTIK ZGO Bielsko-Biała",
      "sets": 1,
      "points_total": 1,
      "points_break": 0,
      "points_balance": 0,
      "serve_total": 1,
      "serve_errors": 0,
      "serve_aces": 0,
      "serve_efficiency": 0,
      "reception_total": 5,
      "reception_errors": 0,
      "reception_positive_percent": 20,
      "reception_perfect_percent": 20,
      "attack_total": 4,
      "attack_errors": 1,
      "attack_blocked": 0,
      "attack_points": 1,
      "attack_success_percent": 25,
      "attack_efficiency": 0,
      "block_points": 0,
      "block_plus": 0,
      "defense": 3,
      "assists": 0,
      "is_home": true,
      "phase": "playoff",
      "home_sets": 3,
      "away_sets": 2,
      "date": "22.04.2025, 17:30",
      "home_team": "PGE Grot Budowlani Łódź",
      "away_team": "BKS BOSTIK ZGO Bielsko-Biała"
    },
    {
      "match_id": null,
      "opponent": "Łącznie (9)",
      "sets": 15,
      "points_total": 21,
      "points_break": 8,
      "points_balance": 12,
      "serve_total": 23,
      "serve_errors": 0,
      "serve_aces": 1,
      "serve_efficiency": 4,
      "reception_total": 65,
      "reception_errors": 4,
      "reception_positive_percent": 29,
      "reception_perfect_percent": 12,
      "attack_total": 59,
      "attack_errors": 5,
      "attack_blocked": 5,
      "attack_points": 17,
      "attack_success_percent": 29,
      "attack_efficiency": 12,
      "block_points": 3,
      "block_plus": 3,
      "defense": 5,
      "assists": 0,
      "is_home": false
    },
    {
      "match_id": null,
      "opponent": "Średnia meczowa",
      "sets": 1.67,
      "points_total": 2.33,
      "points_break": 0.89,
      "points_balance": 1.33,
      "serve_total": 2.56,
      "serve_errors": 0,
      "serve_aces": 0.11,
      "serve_efficiency": 0.48,
      "reception_total": 7.22,
      "reception_errors": 0.44,
      "reception_positive_percent": 3.25,
      "reception_perfect_percent": 1.37,
      "attack_total": 6.56,
      "attack_errors": 0.56,
      "attack_blocked": 0.56,
      "attack_points": 1.89,
      "attack_success_percent": 3.2,
      "attack_efficiency": 1.32,
      "block_points": 0.33,
      "block_plus": 0.33,
      "defense": 0.56,
      "assists": 0,
      "is_home": false
    }
  ],
  "matches_count": 11
}